odoo/addons/attachment_logging/README.rst
odoo/addons/attachment_logging/__init__.py
odoo/addons/attachment_logging/__manifest__.py
odoo/addons/attachment_logging/controllers/__init__.py
odoo/addons/attachment_logging/controllers/main.py
odoo/addons/attachment_logging/data/mail_message_subtype_data.xml
odoo/addons/attachment_logging/i18n/attachment_logging.pot
odoo/addons/attachment_logging/i18n/it.po
odoo/addons/attachment_logging/models/__init__.py
odoo/addons/attachment_logging/models/ir_attachment.py
odoo/addons/attachment_logging/models/res_config_settings.py
odoo/addons/attachment_logging/readme/CONFIGURE.rst
odoo/addons/attachment_logging/readme/CONTRIBUTORS.rst
odoo/addons/attachment_logging/readme/DESCRIPTION.rst
odoo/addons/attachment_logging/readme/USAGE.rst
odoo/addons/attachment_logging/static/description/icon.png
odoo/addons/attachment_logging/static/description/index.html
odoo/addons/attachment_logging/static/src/components/attachment_card/attachment_card.xml
odoo/addons/attachment_logging/static/src/components/attachment_image/attachment_image.xml
odoo/addons/attachment_logging/static/src/img/settings.png
odoo/addons/attachment_logging/static/src/models/attachment.esm.js
odoo/addons/attachment_logging/tests/__init__.py
odoo/addons/attachment_logging/tests/test_ir_attachments.py
odoo/addons/attachment_logging/views/res_config_settings_views.xml
odoo_addon_attachment_logging-16.0.1.0.0.4.dist-info/METADATA
odoo_addon_attachment_logging-16.0.1.0.0.4.dist-info/WHEEL
odoo_addon_attachment_logging-16.0.1.0.0.4.dist-info/top_level.txt
odoo_addon_attachment_logging-16.0.1.0.0.4.dist-info/RECORD
